{
    "Kougasha Magatama":
    {
        "Type": "Sword",
        "Level_Required": 8,
        "Chakra": 3,
        "Defence": 2,
        "Elements": null,
        "Effects":
        {
            "Skill Force": 6
        },
        "Recipe":
        {
            "Sukedachi Sword": 1,
            "Sinister Bones": 3,
            "Large Skull": 1,
            "Fragile Rib": 10,
            "Jaw Bone": 4,
            "Gloom Daruma Fragment": 10,
            "Thick Paper": 1
        }
    },

    "Asougi Magatama":
    {
        "Type": "Sword",
        "Level_Required": 15,
        "Chakra": 6,
        "Defence": 4,
        "Elements": null,
        "Effects":
        {
            "Skill Force": 12
        },
        "Recipe":
        {
            "Nameless Sword": 1,
            "Toad Oil": 3,
            "Toad Stomach": 2,
            "High Grade Toad Oil": 1,
            "Water Plant": 5,
            "Small Geta": 3,
            "Sticky Material": 1,
            "Lotus Spoon": 1,
            "Shell Fragment": 10,
            "Shirikodama": 1
        }
    },

    "Nayuta Magatama":
    {
        "Type": "Sword",
        "Level_Required": 23,
        "Chakra": 10,
        "Defence": 7,
        "Elements": null,
        "Effects":
        {
            "Skill Force": 18
        },
        "Recipe":
        {
            "Ochimusha Sword": 1,
            "Ornate Handle": 3,
            "Peerless Crest": 2,
            "Bloodied Face Guard": 1,
            "Fragile Rib": 10,
            "Jaw Bone": 4,
            "Mountain Water": 5,
            "Small Geta": 3,
            "Sticky Material": 1,
            "Hardy Daikon": 1,
            "Crest Fragment": 10,
            "Rotted Helm": 1
        }
    },

    "Araya Magatama":
    {
        "Type": "Sword",
        "Level_Required": 31,
        "Chakra": 13,
        "Defence": 9,
        "Elements": null,
        "Effects":
        {
            "Skill Force": 25
        },
        "Recipe":
        {
            "Ishikiri Sword": 1,
            "Centipede Feelers": 3,
            "Centidote": 1,
            "Dark Oil": 10,
            "Waxen Fragment": 3,
            "Magical Staff": 1,
            "Broken Lantern": 8,
            "Burnt Talisman": 1,
            "Red Scale": 10,
            "Penanggalan Tail": 1
        }
    },

    "Amara Magatama":
    {
        "Type": "Sword",
        "Level_Required": 38,
        "Chakra": 16,
        "Defence": 11,
        "Elements": null,
        "Effects":
        {
            "Skill Force": 30
        },
        "Recipe":
        {
            "Tatsujin Sword": 1,
            "Wheel": 3,
            "Eternal Torch": 1,
            "Bamboo Strip": 10,
            "Pufferfish Lantern": 2,
            "Baby Centipede Feelers": 10,
            "Putrid Gastric Juice": 1,
            "Baby Fly Wings": 10,
            "Glittering Baby Fly Wings": 1
        }
    },

    "Kouha Magatama":
    {
        "Type": "Sword",
        "Level_Required": 46,
        "Chakra": 19,
        "Defence": 14,
        "Elements": null,
        "Effects":
        {
            "Skill Force": 37
        },
        "Recipe":
        {
            "Helm-Splitter Sword": 1,
            "Sinister Bones": 3,
            "Large Skull": 1,
            "Cotton Strip": 10,
            "Fine Cloth": 2,
            "New Fundoshi": 1,
            "Unkempt Hair": 10,
            "Straw Rope": 1,
            "Spirit Mirror Shard": 10,
            "Eternal Cloud": 1,
            "Baby Centipede Feelers": 10,
            "Putrid Gastric Juice": 1
        }
    },

    "Limitless Spin Magatama":
    {
        "Type": "Sword",
        "Level_Required": 54,
        "Chakra": 22,
        "Defence": 16,
        "Elements": null,
        "Effects":
        {
            "Skill Force": 43
        },
        "Recipe":
        {
            "Fusemachi Sword": 1,
            "Shunoban Horn": 3,
            "Dried Tongue": 1,
            "Giant Cucumber": 10,
            "Punk Kappa Fin": 1,
            "Amagaeru Mucus": 10,
            "Amagaeru Tongue": 1,
            "Crab Pearl": 10,
            "Chestnut Pearl": 1,
            "Bamboo Strip": 10,
            "Pufferfish Lantern": 2
        }
    },

    "Infinite Spin Magatama":
    {
        "Type": "Sword",
        "Level_Required": 62,
        "Chakra": 26,
        "Defence": 19,
        "Elements": null,
        "Effects":
        {
            "Skill Force": 50
        },
        "Recipe":
        {
            "Hakujin Sword": 1,
            "Sinister Bones": 3,
            "Large Skull": 1,
            "Fragile Rib": 10,
            "Jaw Bone": 4,
            "Bamboo Strip": 10,
            "Pufferfish Lantern": 2,
            "Centipede Eggs": 5,
            "Centipede's Poison": 1,
            "Baby Centipede Feelers": 10,
            "Putrid Gastric Juice": 1
        }
    },

    "Unstopped Spin Magatama":
    {
        "Type": "Sword",
        "Level_Required": 69,
        "Chakra": 29,
        "Defence": 21,
        "Elements": null,
        "Effects":
        {
            "Skill Force": 55
        },
        "Recipe":
        {
            "Sunoo Sword": 1,
            "Tep Extract": 3,
            "Tep Flute": 3,
            "Chaos Wasabi": 2,
            "Lively Bulb": 1,
            "Black Body Hair": 3,
            "Skull Mask": 1,
            "Withering Spirit": 10,
            "Lifespan Candle": 1,
            "Red Scale": 10,
            "Penanggalan Tail": 1,
            "Wild Plants": 10,
            "Rock Roots": 1
        }
    },

    "Yujyun Magatama":
    {
        "Type": "Sword",
        "Level_Required": 77,
        "Chakra": 32,
        "Defence": 23,
        "Elements": null,
        "Effects":
        {
            "Skill Force": 62
        }
    },

    "Fukasetsu Magatama":
    {
        "Type": "Sword",
        "Level_Required": 85,
        "Chakra": 35,
        "Defence": 25,
        "Elements": null,
        "Effects":
        {
            "Skill Force": 68
        }
    },

    "Fukasetsu Fukasetsuten Magatama":
    {
        "Type": "Sword",
        "Level_Required": 92,
        "Chakra": 38,
        "Defence": 28,
        "Elements": null,
        "Effects":
        {
            "Skill Force": 74
        }
    },

    "Ronin Magatama":
    {
        "Type": "Sword",
        "Level_Required": 100,
        "Chakra": 40,
        "Defence": 30,
        "Elements": null,
        "Effects":
        {
            "Skill Force": 80
        }
    },

    "Sky Rending Magatama":
    {
        "Type": "Sword",
        "Level_Required": 105,
        "Chakra": 42,
        "Defence": 31,
        "Elements": {"Fire": true, "Rain": false},
        "Effects":
        {
            "Skill Force": 100
        }
    },

    "Sky Rending Magatama - Fused":
    {
        "Type": "Sword",
        "Level_Required": 117,
        "Chakra": 47,
        "Defence": 35,
        "Elements": {"Fire": true, "Lightning": true, "Rain": false, "Mountain": false},
        "Effects":
        {
            "Skill Force": 120
        }
    },

    "Sky Rending Magatama - Tempest":
    {
        "Type": "Sword",
        "Level_Required": 128,
        "Chakra": 51,
        "Defence": 38,
        "Elements": {"Fire": true, "Lightning": true, "Rain": false, "Mountain": false},
        "Effects":
        {
            "Skill Force": 170
        }
    },

    "Tesso Magatama":
    {
        "Type": "Twin Swords",
        "Level_Required": 8,
        "Chakra": 3,
        "Defence": 2,
        "Elements": null,
        "Effects":
        {
            "Skill Force": 6
        },
        "Recipe":
        {
            "Nora Twin Blades": 1,
            "Tricolor Dango": 3,
            "Broken Fishing Rod": 2,
            "Wriggling Moss": 1,
            "Refreshing Leaf": 10,
            "Green Furball": 2,
            "Soft Bill": 1,
            "Pain Daruma Fragment": 10,
            "Dried Abalone": 1
        }
    },

    "Inari Magatama":
    {
        "Type": "Twin Swords",
        "Level_Required": 17,
        "Chakra": 7,
        "Defence": 5,
        "Elements": null,
        "Effects":
        {
            "Skill Force": 14
        },
        "Recipe":
        {
            "Yamaneko Twin Blades": 1,
            "Dried Seaweed": 3,
            "Crab Meat": 2,
            "Cursed Crab Claws": 1,
            "Amagaeru Mucus": 10,
            "Amagaeru Tongue": 1,
            "Toad Oil": 10,
            "Toad Stomach": 1
        }
    },

    "Lion-Dog Magatama":
    {
        "Type": "Twin Swords",
        "Level_Required": 25,
        "Chakra": 10,
        "Defence": 7,
        "Elements": null,
        "Effects":
        {
            "Skill Force": 20
        },
        "Recipe":
        {
            "Arawashi Twin Blades": 1,
            "Unkempt Hair": 3,
            "Straw Rope": 1,
            "Baby Centipede Feelers": 10,
            "Putrid Gastric Juice": 1,
            "Jiggling Meat": 8,
            "Melting Meat": 1,
            "Water Plant": 5,
            "Small Geta": 3,
            "Sticky Material": 1,
            "Lotus Spoon": 1
        }
    },

    "Nekomata Magatama":
    {
        "Type": "Twin Swords",
        "Level_Required": 33,
        "Chakra": 13,
        "Defence": 10,
        "Elements": null,
        "Effects":
        {
            "Skill Force": 26
        },
        "Recipe":
        {
            "Kokuto Twin Blades": 1,
            "Iron Sand": 3,
            "Nue Heart": 2,
            "Nue's Cry": 1,
            "Fragile Rib": 10,
            "Jaw Bone": 4,
            "Unkempt Hair": 10,
            "Straw Rope": 1,
            "Giant Cucumber": 10,
            "Punk Kappa Fin": 1
        }
    },

    "Fuuri Magatama":
    {
        "Type": "Twin Swords",
        "Level_Required": 42,
        "Chakra": 17,
        "Defence": 13,
        "Elements": null,
        "Effects":
        {
            "Skill Force": 34
        },
        "Recipe":
        {
            "Tokage Twin Blades": 1,
            "Crushed Nail": 3,
            "Cursed Blood": 1,
            "Toad Oil": 10,
            "Toad Stomach": 1,
            "Giant Cucumber": 10,
            "Punk Kappa Fin": 1,
            "Fragile Rib": 10,
            "Jaw Bone": 4,
            "Gloom Daruma Fragment": 10,
            "Thick Paper": 1
        }
    },

    "Zhen Magatama":
    {
        "Type": "Twin Swords",
        "Level_Required": 50,
        "Chakra": 20,
        "Defence": 15,
        "Elements": null,
        "Effects":
        {
            "Skill Force": 40
        },
        "Recipe":
        {
            "Tiger Claw Twin Blades": 1,
            "Dried Seaweed": 3,
            "Crab Meat": 2,
            "Cursed Crab Claws": 1,
            "Toad Oil": 10,
            "Toad Stomach": 1,
            "Jiggling Meat": 8,
            "Melting Meat": 1,
            "Fragile Rib": 10,
            "Jaw Bone": 4,
            "Shell Fragment": 10,
            "Shirikodama": 1
        }
    },

    "Shouko Magatama":
    {
        "Type": "Twin Swords",
        "Level_Required": 58,
        "Chakra": 23,
        "Defence": 17,
        "Elements": null,
        "Effects":
        {
            "Skill Force": 46
        },
        "Recipe":
        {
            "Seiu Twin Blades": 1,
            "Sickle Whetstone": 3,
            "Herbissacre": 1,
            "Centipede Eggs": 5,
            "Centipede's Poison": 1,
            "Wheel": 10,
            "Eternal Torch": 1,
            "Wild Plants": 10,
            "Rock Roots": 1,
            "Baby Centipede Feelers": 10,
            "Putrid Gastric Juice": 1
        }
    },

    "Enku Magatama":
    {
        "Type": "Twin Swords",
        "Level_Required": 67,
        "Chakra": 27,
        "Defence": 20,
        "Elements": null,
        "Effects":
        {
            "Skill Force": 54
        },
        "Recipe":
        {
            "Inugaminotou": 1,
            "New Pacifier": 3,
            "Skull Remote": 2,
            "Green Doppelganger Mushroom": 1,
            "Centipede Fluids": 10,
            "Potent Venom": 1,
            "Refreshing Leaf": 10,
            "Green Furball": 2,
            "Soft Bill": 1,
            "Pumice Stone": 10,
            "Maple Leaf": 1,
            "Tricolor Dango": 10,
            "Broken Fishing Rod": 3,
            "Wriggling Moss": 1
        }
    },

    "Kirin Magatama":
    {
        "Type": "Twin Swords",
        "Level_Required": 75,
        "Chakra": 30,
        "Defence": 22,
        "Elements": null,
        "Effects":
        {
            "Skill Force": 60
        }
    },

    "Tankaku Magatama":
    {
        "Type": "Twin Swords",
        "Level_Required": 83,
        "Chakra": 33,
        "Defence": 25,
        "Elements": null,
        "Effects":
        {
            "Skill Force": 66
        }
    },

    "Sakumei Magatama":
    {
        "Type": "Twin Swords",
        "Level_Required": 92,
        "Chakra": 37,
        "Defence": 28,
        "Elements": null,
        "Effects":
        {
            "Skill Force": 74
        }
    },

    "Hunter's Magatama":
    {
        "Type": "Twin Swords",
        "Level_Required": 100,
        "Chakra": 40,
        "Defence": 30,
        "Elements": null,
        "Effects":
        {
            "Skill Force": 80
        }
    },

    "Dancing Water Magatama":
    {
        "Type": "Twin Swords",
        "Level_Required": 105,
        "Chakra": 42,
        "Defence": 31,
        "Elements": {"Ice": true, "Fire": false},
        "Effects":
        {
            "Skill Force": 100
        }
    },

    "Dancing Water Magatama - Fused":
    {
        "Type": "Twin Swords",
        "Level_Required": 117,
        "Chakra": 47,
        "Defence": 35,
        "Elements": {"Ice": true, "Rain": true, "Fire": false, "Lightning": false},
        "Effects":
        {
            "Skill Force": 120
        }
    },

    "Dancing Water Magatama - Tempest":
    {
        "Type": "Twin Swords",
        "Level_Required": 128,
        "Chakra": 51,
        "Defence": 38,
        "Elements": {"Ice": true, "Rain": true, "Fire": false, "Lightning": false},
        "Effects":
        {
            "Skill Force": 170
        }
    },

    "Tasogare Magatama":
    {
        "Type": "Odachi",
        "Level_Required": 8,
        "Chakra": 3,
        "Defence": 2,
        "Elements": null,
        "Effects":
        {
            "Skill Force": 6
        },
        "Recipe":
        {
            "Nodachi": 1,
            "Broken Lantern": 3,
            "Burnt Talisman": 1,
            "Bug Repellant Coil": 5,
            "Small Geta": 3,
            "Sticky Material": 1,
            "Healthy Drink Powder": 1,
            "Pumice Stone": 10,
            "Maple Leaf": 1
        }
    },

    "Yoake Magatama":
    {
        "Type": "Odachi",
        "Level_Required": 15,
        "Chakra": 6,
        "Defence": 4,
        "Elements": null,
        "Effects":
        {
            "Skill Force": 12
        },
        "Recipe":
        {
            "Oshikiri Tachi": 1,
            "Bamboo Strip": 3,
            "Pufferfish Lantern": 1,
            "Jiggling Meat": 8,
            "Melting Meat": 1,
            "Tricolor Dango": 10,
            "Broken Fishing Rod": 3,
            "Wriggling Moss": 1
        }
    },

    "Sougyou Magatama":
    {
        "Type": "Odachi",
        "Level_Required": 23,
        "Chakra": 10,
        "Defence": 7,
        "Elements": null,
        "Effects":
        {
            "Skill Force": 18
        },
        "Recipe":
        {
            "Araburi Tachi": 1,
            "Hiderigami's Sigh": 3,
            "Scorching Furnace": 1,
            "Shell Fragment": 10,
            "Shirikodama": 1,
            "Giant Cucumber": 10,
            "Punk Kappa Fin": 1,
            "Amagaeru Mucus": 10,
            "Amagaeru Tongue": 1
        }
    },

    "Akebono Magatama":
    {
        "Type": "Odachi",
        "Level_Required": 31,
        "Chakra": 13,
        "Defence": 9,
        "Elements": null,
        "Effects":
        {
            "Skill Force": 25
        },
        "Recipe":
        {
            "Ariake Tachi": 1,
            "Bronze Fragment": 3,
            "Decorative Legs": 1,
            "Amagaeru Mucus": 10,
            "Amagaeru Tongue": 1,
            "Crab Pearl": 10,
            "Chestnut Pearl": 1,
            "Life Daruma Fragment": 10,
            "Gift Bag": 1
        }
    },

    "Dusk Magatama":
    {
        "Type": "Odachi",
        "Level_Required": 38,
        "Chakra": 16,
        "Defence": 11,
        "Elements": null,
        "Effects":
        {
            "Skill Force": 30
        },
        "Recipe":
        {
            "Nyuudou Tachi": 1,
            "Gypsum": 3,
            "Onigawara": 1,
            "Spirit Mirror Shard": 10,
            "Eternal Cloud": 1,
            "Yagyou-san's Tears":  8,
            "Ancient Coin": 1,
            "Bristly Beard": 10,
            "Tanuki Tail": 1
        }
    },

    "Shinonome Magatama":
    {
        "Type": "Odachi",
        "Level_Required": 46,
        "Chakra": 19,
        "Defence": 14,
        "Elements": null,
        "Effects":
        {
            "Skill Force": 37
        },
        "Recipe":
        {
            "Ikkaku Tachi": 1,
            "Sulfur": 3,
            "Reversed Compass": 1,
            "Luck Daruma Fragment": 10,
            "Daifuku": 1,
            "Loss Daruma Fragment": 10,
            "Ink": 1,
            "Mountain Water": 5,
            "Small Geta": 6,
            "Sticky Material": 2,
            "Hardy Daikon": 1,
            "Crow Feather": 5,
            "Blackened Rose-coloured Glasses": 1
        }
    },

    "Fuugyou Magatama":
    {
        "Type": "Odachi",
        "Level_Required": 54,
        "Chakra": 22,
        "Defence": 16,
        "Elements": null,
        "Effects":
        {
            "Skill Force": 43
        },
        "Recipe":
        {
            "Touda Tachi": 1,
            "Sickle Whetstone": 3,
            "Herbissacre": 1,
            "Bristly Beard": 10,
            "Tanuki Tail": 1,
            "Dark Oil": 10,
            "Waxen Fragment": 3,
            "Magical Staff": 1,
            "Centipede Feelers": 10,
            "Centidote": 1,
            "Old Thread": 10,
            "Bell of the Curse God": 1
        }
    },

    "Ariake Magatama":
    {
        "Type": "Odachi",
        "Level_Required": 62,
        "Chakra": 26,
        "Defence": 19,
        "Elements": null,
        "Effects":
        {
            "Skill Force": 50
        },
        "Recipe":
        {
            "Yasha Tachi": 1,
            "Sinister Bones": 3,
            "Large Skull": 1,
            "Toad Oil": 10,
            "Toad Stomach": 1,
            "Dark Oil": 10,
            "Waxen Fragment": 3,
            "Magical Staff": 1,
            "Red Dyes": 8,
            "Red Claw": 8,
            "Bamboo Rotocoptor": 1,
            "Old Thread": 10,
            "Bell of the Curse God": 1
        }
    },

    "Reimei Magatama":
    {
        "Type": "Odachi",
        "Level_Required": 69,
        "Chakra": 29,
        "Defence": 21,
        "Elements": null,
        "Effects":
        {
            "Skill Force": 55
        },
        "Recipe":
        {
            "Rasetsu Tachi": 1,
            "Tep Extract": 3,
            "Tep Flute": 3,
            "Chaos Wasabi": 2,
            "Lively Bulb": 1,
            "Gypsum": 10,
            "Onigawara": 1,
            "Cotton Strip": 10,
            "Fine Cloth": 2,
            "New Fundoshi": 1,
            "Unkempt Hair": 10,
            "Straw Rope": 1,
            "Shell Fragment": 10,
            "Shirikodama": 1
        }
    },

    "Hakubo Magatama":
    {
        "Type": "Odachi",
        "Level_Required": 77,
        "Chakra": 32,
        "Defence": 23,
        "Elements": null,
        "Effects":
        {
            "Skill Force": 62
        }
    },

    "Kawatare Magatama":
    {
        "Type": "Odachi",
        "Level_Required": 85,
        "Chakra": 35,
        "Defence": 25,
        "Elements": null,
        "Effects":
        {
            "Skill Force": 68
        }
    },

    "Akatsuki Magatama":
    {
        "Type": "Odachi",
        "Level_Required": 92,
        "Chakra": 38,
        "Defence": 28,
        "Elements": null,
        "Effects":
        {
            "Skill Force": 74
        }
    },

    "Heroic Magatama":
    {
        "Type": "Odachi",
        "Level_Required": 100,
        "Chakra": 40,
        "Defence": 30,
        "Elements": null,
        "Effects":
        {
            "Skill Force": 80
        }
    },

    "Wicked Wolf Magatama":
    {
        "Type": "Odachi",
        "Level_Required": 105,
        "Chakra": 42,
        "Defence": 31,
        "Elements": {"Wind": true, "Ice": false},
        "Effects":
        {
            "Skill Force": 100
        }
    },

    "Wicked Wolf Magatama - Fused":
    {
        "Type": "Odachi",
        "Level_Required": 117,
        "Chakra": 47,
        "Defence": 35,
        "Elements": {"Wind": true, "Fire": true, "Ice": false, "Rain": false},
        "Effects":
        {
            "Skill Force": 120
        }
    },

    "Wicked Wolf Magatama - Tempest":
    {
        "Type": "Odachi",
        "Level_Required": 128,
        "Chakra": 51,
        "Defence": 38,
        "Elements": {"Wind": true, "Fire": true, "Ice": false, "Rain": false},
        "Effects":
        {
            "Skill Force": 170
        }
    },

    "Mikan Magatama":
    {
        "Type": "Bow",
        "Level_Required": 9,
        "Chakra": 4,
        "Defence": 3,
        "Elements": null,
        "Effects":
        {
            "Skill Force": 7
        },
        "Recipe":
        {
            "Fledgling Sparrow Bow": 1,
            "Shunoban Horn": 3,
            "Dried Tongue": 1,
            "Luck Daruma Fragment": 10,
            "Daifuku": 1,
            "Mountain Water": 5,
            "Small Geta": 3,
            "Sticky Material": 1,
            "Hardy Daikon": 1
        }
    },

    "Banana Magatama":
    {
        "Type": "Bow",
        "Level_Required": 18,
        "Chakra": 7,
        "Defence": 5,
        "Elements": null,
        "Effects":
        {
            "Skill Force": 14
        },
        "Recipe":
        {
            "Heavy Rattan Bow": 1,
            "Gypsum": 3,
            "Onigawara": 1,
            "Giant Cucumber": 10,
            "Punk Kappa Fin": 1,
            "Bristly Beard": 10,
            "Tanuki Tail": 1
        }
    },

    "Pineapple Magatama":
    {
        "Type": "Bow",
        "Level_Required": 27,
        "Chakra": 11,
        "Defence": 8,
        "Elements": null,
        "Effects":
        {
            "Skill Force": 22
        },
        "Recipe":
        {
            "Fuedou Bow": 1,
            "Broken Lantern": 3,
            "Burnt Talisman": 1,
            "Toad Oil": 10,
            "Toad Stomach": 1,
            "Gloom Daruma Fragment": 10,
            "Thick Paper": 1,
            "Tart Peach": 5,
            "Small Geta": 3,
            "Sticky Material": 1,
            "White Peach Pudding": 1
        }
    },

    "Melon Magatama":
    {
        "Type": "Bow",
        "Level_Required": 36,
        "Chakra": 14,
        "Defence": 11,
        "Elements": null,
        "Effects":
        {
            "Skill Force": 29
        },
        "Recipe":
        {
            "Black Pine Bow": 1,
            "Sulfur": 3,
            "Reversed Compass": 1,
            "Gypsum": 10,
            "Onigawara": 1,
            "Crest Fragment": 10,
            "Rotted Helm": 1,
            "Luck Daruma Fragment": 10,
            "Daifuku": 1
        }
    },

    "Grape Magatama":
    {
        "Type": "Bow",
        "Level_Required": 45,
        "Chakra": 18,
        "Defence": 13,
        "Elements": null,
        "Effects":
        {
            "Skill Force": 36
        },
        "Recipe":
        {
            "Minamoto Bow": 1,
            "Black Moth Scales": 3,
            "Gray Apple": 1,
            "Crest Fragment": 10,
            "Rotted Helm": 1,
            "Jiggling Meat": 8,
            "Melting Meat": 1,
            "Black Body Hair": 3,
            "Skull Mask": 1,
            "Cat Whiskers": 8,
            "Cat Pawprint": 1
        }
    },

    "Strawberry Magatama":
    {
        "Type": "Bow",
        "Level_Required": 55,
        "Chakra": 22,
        "Defence": 16,
        "Elements": null,
        "Effects":
        {
            "Skill Force": 44
        },
        "Recipe":
        {
            "Yuusai Bow": 1,
            "Spiked Collar": 3,
            "Honey": 2,
            "Cerberus Vinegar": 1,
            "Iron Sand": 10,
            "Nue Heart": 1,
            "Centipede Fluids": 10,
            "Potent Venom": 1,
            "Charcoal": 10,
            "Diamond Dust": 1,
            "Bug Repellant Coil": 5,
            "Small Geta": 3,
            "Sticky Material": 1,
            "Healthy Drink Powder": 1
        }
    },

    "Watermelon Magatama":
    {
        "Type": "Bow",
        "Level_Required": 64,
        "Chakra": 26,
        "Defence": 19,
        "Elements": null,
        "Effects":
        {
            "Skill Force": 51
        },
        "Recipe":
        {
            "Mino Bow": 1,
            "Venemous Lipstick": 3,
            "Pink Match": 2,
            "Magical Hand Mirror": 1,
            "Jiggling Meat": 8,
            "Melting Meat": 1,
            "Baby Bottle": 10,
            "Childbirth Amulet": 2,
            "Ubume Nest": 1,
            "Dried Seaweed": 10,
            "Crab Meat": 1,
            "Crab Pearl": 10,
            "Chestnut Pearl": 1
        }
    },

    "Mango Magatama":
    {
        "Type": "Bow",
        "Level_Required": 73,
        "Chakra": 29,
        "Defence": 22,
        "Elements": null,
        "Effects":
        {
            "Skill Force": 58
        }
    },

    "Lemon Magatama":
    {
        "Type": "Bow",
        "Level_Required": 82,
        "Chakra": 33,
        "Defence": 25,
        "Elements": null,
        "Effects":
        {
            "Skill Force": 66
        }
    },

    "Durian Magatama":
    {
        "Type": "Bow",
        "Level_Required": 91,
        "Chakra": 36,
        "Defence": 27,
        "Elements": null,
        "Effects":
        {
            "Skill Force": 73
        }
    },

    "Pressure Point Magatama":
    {
        "Type": "Bow",
        "Level_Required": 100,
        "Chakra": 40,
        "Defence": 30,
        "Elements": null,
        "Effects":
        {
            "Skill Force": 80
        }
    },

    "Attack Star Magatama":
    {
        "Type": "Bow",
        "Level_Required": 105,
        "Chakra": 42,
        "Defence": 31,
        "Elements": {"Rain": true, "Lightning": false},
        "Effects":
        {
            "Skill Force": 100
        }
    },

    "Attack Star Magatama - Fused":
    {
        "Type": "Bow",
        "Level_Required": 117,
        "Chakra": 47,
        "Defence": 35,
        "Elements": {"Rain": true, "Mountain": true, "Lightning": false, "Wind": false},
        "Effects":
        {
            "Skill Force": 120
        }
    },

    "Attack Star Magatama - Tempest":
    {
        "Type": "Bow",
        "Level_Required": 128,
        "Chakra": 51,
        "Defence": 38,
        "Elements": {"Rain": true, "Mountain": true, "Lightning": false, "Wind": false},
        "Effects":
        {
            "Skill Force": 170
        }
    },

    "Bonnou Magatama":
    {
        "Type": "Axe",
        "Level_Required": 8,
        "Chakra": 3,
        "Defence": 2,
        "Elements": null,
        "Effects":
        {
            "Skill Force": 6
        },
        "Recipe":
        {
            "Stone Battleaxe": 1,
            "Crab Pearl": 3,
            "Chestnut Pearl": 1,
            "Orange Peel Juice": 5,
            "Small Geta": 3,
            "Sticky Material": 1,
            "Twilight Melancholy": 1,
            "Shell Fragment": 10,
            "Shirikodama": 1
        }
    },

    "Oumagatoki Magatama":
    {
        "Type": "Axe",
        "Level_Required": 15,
        "Chakra": 6,
        "Defence": 4,
        "Elements": null,
        "Effects":
        {
            "Skill Force": 12
        },
        "Recipe":
        {
            "Iron Battleaxe": 1,
            "Dark Oil": 3,
            "Waxen Fragment": 2,
            "Purified Oil": 1,
            "Crest Fragment": 10,
            "Rotted Helm": 1,
            "Fragile Rib": 10,
            "Jaw Bone": 4
        }
    },

    "Hangon Magatama":
    {
        "Type": "Axe",
        "Level_Required": 23,
        "Chakra": 10,
        "Defence": 7,
        "Elements": null,
        "Effects":
        {
            "Skill Force": 18
        },
        "Recipe":
        {
            "Rusted Battleaxe": 1,
            "Yagyou-san's Tears": 3,
            "Ancient Coin": 1,
            "Dark Oil": 10,
            "Waxen Fragment": 3,
            "Magical Staff": 1,
            "Cat Whiskers": 8,
            "Cat Pawprint": 1,
            "Life Daruma Fragment": 10,
            "Gift Bag": 1
        }
    },

    "Gedatsu Magatama":
    {
        "Type": "Axe",
        "Level_Required": 31,
        "Chakra": 13,
        "Defence": 9,
        "Elements": null,
        "Effects":
        {
            "Skill Force": 25
        },
        "Recipe":
        {
            "Seidou Battleaxe": 1,
            "Centipede Feelers": 3,
            "Centidote": 1,
            "Loss Daruma Fragment": 10,
            "Ink": 1,
            "Mountain Water": 5,
            "Small Geta": 3,
            "Sticky Material": 1,
            "Hardy Daikon": 1,
            "Jiggling Meat": 8,
            "Melting Meat": 1
        }
    },

    "Konron Magatama":
    {
        "Type": "Axe",
        "Level_Required": 38,
        "Chakra": 16,
        "Defence": 11,
        "Elements": null,
        "Effects":
        {
            "Skill Force": 30
        },
        "Recipe":
        {
            "Steel Battleaxe": 1,
            "Wheel": 3,
            "Eternal Torch": 1,
            "Black Body Hair": 3,
            "Skull Mask": 1,
            "Centipede Fluids": 10,
            "Potent Venom": 1,
            "Dark Oil": 10,
            "Waxen Fragment": 3,
            "Magical Staff": 1
        }
    },

    "Kakuryo Magatama":
    {
        "Type": "Axe",
        "Level_Required": 46,
        "Chakra": 19,
        "Defence": 14,
        "Elements": null,
        "Effects":
        {
            "Skill Force": 37
        },
        "Recipe":
        {
            "Sekkou Battleaxe": 1,
            "Daruma's Pipe": 3,
            "Embroidered Cushion": 1,
            "Red Scale": 10,
            "Penanggalan Tail": 1,
            "Old Thread": 10,
            "Bell of the Curse God": 1,
            "Ashes": 20,
            "Paper Helmet": 10,
            "Star Ornament": 1,
            "Paper Helmet": 10,
            "Star Ornament": 1
        }
    },

    "Houzen Magatama":
    {
        "Type": "Axe",
        "Level_Required": 54,
        "Chakra": 22,
        "Defence": 16,
        "Elements": null,
        "Effects":
        {
            "Skill Force": 43
        },
        "Recipe":
        {
            "Sekinseki Battleaxe": 1,
            "Spiked Collar": 3,
            "Honey": 2,
            "Cerberus Vinegar": 1,
            "Red Scale": 10,
            "Penanggalan Tail": 1,
            "Nozuchi Stomach Acid": 10,
            "Matsutake Mushroom": 1,
            "Spirit Mirror Shard": 10,
            "Eternal Cloud": 1,
            "Unkempt Hair": 10,
            "Straw Rope": 1
        }
    },

    "Himorogi Magatama":
    {
        "Type": "Axe",
        "Level_Required": 62,
        "Chakra": 26,
        "Defence": 19,
        "Elements": null,
        "Effects":
        {
            "Skill Force": 50
        },
        "Recipe":
        {
            "Quartz Battleaxe": 1,
            "Sinister Bones": 3,
            "Large Skull": 1,
            "Nozuchi Stomach Acid": 10,
            "Matsutake Mushroom": 1,
            "Crest Fragment": 10,
            "Rotted Helm": 1,
            "Giant Cucumber": 10,
            "Punk Kappa Fin": 1,
            "Broken Lantern": 8,
            "Burnt Talisman": 1
        }
    },

    "Wadatsumi Magatama":
    {
        "Type": "Axe",
        "Level_Required": 69,
        "Chakra": 29,
        "Defence": 21,
        "Elements": null,
        "Effects":
        {
            "Skill Force": 55
        },
        "Recipe":
        {
            "Genbugan Battleaxe": 1,
            "Tep Extract": 3,
            "Tep Flute": 3,
            "Chaos Wasabi": 2,
            "Lively Bulb": 1,
            "Fletching": 10,
            "Silk Bag": 1,
            "Charcoal": 10,
            "Diamond Dust": 1,
            "Fragile Rib": 10,
            "Jaw Bone": 4,
            "Bamboo Strip": 10,
            "Pufferfish Lantern": 2
        }
    },

    "Gokuraku Magatama":
    {
        "Type": "Axe",
        "Level_Required": 77,
        "Chakra": 32,
        "Defence": 23,
        "Elements": null,
        "Effects":
        {
            "Skill Force": 62
        }
    },

    "Nehan Magatama":
    {
        "Type": "Axe",
        "Level_Required": 85,
        "Chakra": 35,
        "Defence": 25,
        "Elements": null,
        "Effects":
        {
            "Skill Force": 68
        }
    },

    "Rinne Magatama":
    {
        "Type": "Axe",
        "Level_Required": 92,
        "Chakra": 38,
        "Defence": 28,
        "Elements": null,
        "Effects":
        {
            "Skill Force": 74
        }
    },

    "Bloody Festival Magatama":
    {
        "Type": "Axe",
        "Level_Required": 100,
        "Chakra": 40,
        "Defence": 30,
        "Elements": null,
        "Effects":
        {
            "Skill Force": 80
        }
    },

    "Raretsu Magatama":
    {
        "Type": "Axe",
        "Level_Required": 105,
        "Chakra": 42,
        "Defence": 31,
        "Elements": {"Mountain": true, "Wind": false},
        "Effects":
        {
            "Skill Force": 100
        }
    },

    "Raretsu Magatama - Fused":
    {
        "Type": "Axe",
        "Level_Required": 117,
        "Chakra": 47,
        "Defence": 35,
        "Elements": {"Mountain": true, "Ice": true, "Wind": false, "Fire": false},
        "Effects":
        {
            "Skill Force": 120
        }
    },

    "Raretsu Magatama - Tempest":
    {
        "Type": "Axe",
        "Level_Required": 128,
        "Chakra": 51,
        "Defence": 38,
        "Elements": {"Mountain": true, "Ice": true, "Wind": false, "Fire": false},
        "Effects":
        {
            "Skill Force": 170
        }
    },

    "Aries Magatama":
    {
        "Type": "Spear",
        "Level_Required": 8,
        "Chakra": 3,
        "Defence": 2,
        "Elements": null,
        "Effects":
        {
            "Skill Force": 6
        },
        "Recipe":
        {
            "Cedar Spear": 1,
            "Giant Cucumber": 3,
            "Punk Kappa Fin": 1,
            "Cotton Strip": 10,
            "Fine Cloth": 2,
            "New Fundoshi": 1,
            "Water Plant": 5,
            "Small Geta": 3,
            "Sticky Material": 1,
            "Lotus Spoon": 1
        }
    },

    "Taurus Magatama":
    {
        "Type": "Spear",
        "Level_Required": 15,
        "Chakra": 6,
        "Defence": 4,
        "Elements": null,
        "Effects":
        {
            "Skill Force": 12
        },
        "Recipe":
        {
            "Gingko Spear": 1,
            "Crest Fragment": 3,
            "Rotted Helm": 2,
            "Bloodied Face Guard": 1,
            "Bamboo Strip": 10,
            "Pufferfish Lantern": 2,
            "Mountain Water": 5,
            "Small Geta": 3,
            "Sticky Material": 1,
            "Hardy Daikon": 1
        }
    },

    "Gemini Magatama":
    {
        "Type": "Spear",
        "Level_Required": 23,
        "Chakra": 10,
        "Defence": 7,
        "Elements": null,
        "Effects":
        {
            "Skill Force": 18
        },
        "Recipe":
        {
            "Adorned Bamboo Spear": 1,
            "Black Moth Scales": 3,
            "Gray Apple": 1,
            "Bamboo Strip": 10,
            "Pufferfish Lantern": 2,
            "Luck Daruma Fragment": 10,
            "Daifuku": 1,
            "Loss Daruma Fragment": 10,
            "Ink": 1
        }
    },

    "Cancer Magatama":
    {
        "Type": "Spear",
        "Level_Required": 31,
        "Chakra": 13,
        "Defence": 9,
        "Elements": null,
        "Effects":
        {
            "Skill Force": 25
        },
        "Recipe":
        {
            "Red Lacquer Spear": 1,
            "Iron Sand": 3,
            "Nue Heart": 2,
            "Nue's Cry": 1,
            "Broken Lantern": 8,
            "Burnt Talisman": 1,
            "Red Scale": 10,
            "Penanggalan Tail": 1,
            "Bamboo Strip": 10,
            "Pufferfish Lantern": 2
        }
    },

    "Leo Magatama":
    {
        "Type": "Spear",
        "Level_Required": 38,
        "Chakra": 16,
        "Defence": 11,
        "Elements": null,
        "Effects":
        {
            "Skill Force": 30
        },
        "Recipe":
        {
            "Maple Spear": 1,
            "Bronze Fragment": 3,
            "Decorative Legs": 1,
            "Baby Centipede Feelers": 10,
            "Putrid Gastric Juice": 1,
            "Baby Fly Wings": 10,
            "Glittering Baby Fly Wings": 1,
            "Fragile Rib": 10,
            "Jaw Bone": 4
        }
    },

    "Virgo Magatama":
    {
        "Type": "Spear",
        "Level_Required": 46,
        "Chakra": 19,
        "Defence": 14,
        "Elements": null,
        "Effects":
        {
            "Skill Force": 37
        },
        "Recipe":
        {
            "Chained Magnolia Spear": 1,
            "Pale Colored Scale": 3,
            "Pale Colored Thorn": 1,
            "Ashes": 20,
            "Paper Crane": 10,
            "Warding Peach": 1,
            "Iron Sand": 10,
            "Nue Heart": 1,
            "Mantra": 1,
            "Bamboo Strip": 10,
            "Pufferfish Lantern": 2
        }
    },

    "Libra Magatama":
    {
        "Type": "Spear",
        "Level_Required": 54,
        "Chakra": 22,
        "Defence": 16,
        "Elements": null,
        "Effects":
        {
            "Skill Force": 43
        },
        "Recipe":
        {
            "Shouinmatsu Spear": 1,
            "Spiked Collar": 3,
            "Honey": 2,
            "Cerberus Vinegar": 1,
            "Black Body Hair": 3,
            "Skull Mask": 1,
            "Withering Spirit": 10,
            "Lifespan Candle": 1,
            "Giant Cucumber": 10,
            "Punk Kappa Fin": 1,
            "Amagaeru Mucus": 10,
            "Amagaeru Tongue": 1
        }
    },

    "Scorpio Magatama":
    {
        "Type": "Spear",
        "Level_Required": 62,
        "Chakra": 26,
        "Defence": 19,
        "Elements": null,
        "Effects":
        {
            "Skill Force": 50
        },
        "Recipe":
        {
            "Scaled Walnut Spear": 1,
            "Sinister Bones": 3,
            "Large Skull": 1,
            "Centipede Eggs": 5,
            "Centipede's Poison": 1,
            "Baby Centipede Feelers": 10,
            "Putrid Gastric Juice": 1,
            "Black Body Hair": 3,
            "Skull Mask": 1,
            "Withering Spirit": 10,
            "Lifespan Candle": 1
        }
    },

    "Sagittarius Magatama":
    {
        "Type": "Spear",
        "Level_Required": 69,
        "Chakra": 29,
        "Defence": 21,
        "Elements": null,
        "Effects":
        {
            "Skill Force": 55
        },
        "Recipe":
        {
            "Ash Spear": 1,
            "Tep Extract": 3,
            "Tep Flute": 3,
            "Chaos Wasabi": 2,
            "Lively Bulb": 1,
            "Red Scale": 10,
            "Penanggalan Tail": 1,
            "Wild Plants": 10,
            "Rock Roots": 1,
            "Centipede Fluids": 10,
            "Potent Venom": 1,
            "Refreshing Leaf": 10,
            "Green Furball": 2,
            "Soft Bill": 1
        }
    },

    "Capricorn Magatama":
    {
        "Type": "Spear",
        "Level_Required": 77,
        "Chakra": 32,
        "Defence": 23,
        "Elements": null,
        "Effects":
        {
            "Skill Force": 62
        }
    },

    "Aquarius Magatama":
    {
        "Type": "Spear",
        "Level_Required": 85,
        "Chakra": 35,
        "Defence": 25,
        "Elements": null,
        "Effects":
        {
            "Skill Force": 68
        }
    },

    "Pisces Magatama":
    {
        "Type": "Spear",
        "Level_Required": 92,
        "Chakra": 38,
        "Defence": 28,
        "Elements": null,
        "Effects":
        {
            "Skill Force": 74
        }
    },

    "Log Magatama":
    {
        "Type": "Spear",
        "Level_Required": 100,
        "Chakra": 40,
        "Defence": 30,
        "Elements": null,
        "Effects":
        {
            "Skill Force": 80
        }
    },

    "Thunder Quake Magatama":
    {
        "Type": "Spear",
        "Level_Required": 105,
        "Chakra": 42,
        "Defence": 31,
        "Elements": {"Lightning": true, "Mountain": false},
        "Effects":
        {
            "Skill Force": 100
        }
    },

    "Thunder Quake Magatama - Fused":
    {
        "Type": "Spear",
        "Level_Required": 117,
        "Chakra": 47,
        "Defence": 35,
        "Elements": {"Lightning": true, "Wind": true, "Mountain": false, "Ice": false},
        "Effects":
        {
            "Skill Force": 120
        }
    },

    "Thunder Quake Magatama - Tempest":
    {
        "Type": "Spear",
        "Level_Required": 128,
        "Chakra": 51,
        "Defence": 38,
        "Elements": {"Lightning": true, "Wind": true, "Mountain": false, "Ice": false},
        "Effects":
        {
            "Skill Force": 170
        }
    },

    "Lord Shinkou Magatama":
    {
        "Type": "Wand",
        "Level_Required": 7,
        "Chakra": 3,
        "Defence": 2,
        "Elements": null,
        "Effects":
        {
            "Skill Force": 6
        },
        "Recipe":
        {
            "Manjusri Talisman": 1,
            "Gypsum": 3,
            "Onigawara": 1,
            "Amagaeru Mucus": 10,
            "Amagaeru Tongue": 1,
            "Crest Fragment": 10,
            "Rotted Helm": 1
        }
    },

    "Lord Shokou Magatama":
    {
        "Type": "Wand",
        "Level_Required": 14,
        "Chakra": 6,
        "Defence": 4,
        "Elements": null,
        "Effects":
        {
            "Skill Force": 11
        },
        "Recipe":
        {
            "Jizou Talisman": 1,
            "Pale Colored Scale": 3,
            "Pale Colored Thorn": 1,
            "Baby Centipede Feelers": 10,
            "Putrid Gastric Juice": 1,
            "Orange Peel Juice": 5,
            "Small Geta": 3,
            "Sticky Material": 1,
            "Twilight Melancholy": 1
        }
    },

    "Lord Soutei Magatama":
    {
        "Type": "Wand",
        "Level_Required": 21,
        "Chakra": 8,
        "Defence": 6,
        "Elements": null,
        "Effects":
        {
            "Skill Force": 17
        },
        "Recipe":
        {
            "Sunlight Talisman": 1,
            "Ornate Handle": 3,
            "Peerless Crest": 2,
            "Bloodied Face Guard": 1,
            "Bristly Beard": 10,
            "Tanuki Tail": 1,
            "Gypsum": 10,
            "Onigawara": 1,
            "Crow Feather": 5,
            "Small Geta": 3,
            "Sticky Material": 1,
            "Blackened Rose-coloured Glasses": 1
        }
    },

    "Lord Gokan Magatama":
    {
        "Type": "Wand",
        "Level_Required": 29,
        "Chakra": 12,
        "Defence": 9,
        "Elements": null,
        "Effects":
        {
            "Skill Force": 23
        },
        "Recipe":
        {
            "Moonlight Talisman": 1,
            "Unkempt Hair": 3,
            "Straw Rope": 1,
            "Spirit Mirror Shard": 10,
            "Eternal Cloud": 1,
            "Fragile Rib": 10,
            "Jaw Bone": 4,
            "Mountain Water": 5,
            "Small Geta": 3,
            "Sticky Material": 1,
            "Hardy Daikon": 1
        }
    },

    "Lord Enma Magatama":
    {
        "Type": "Wand",
        "Level_Required": 36,
        "Chakra": 14,
        "Defence": 11,
        "Elements": null,
        "Effects":
        {
            "Skill Force": 29
        },
        "Recipe":
        {
            "Kisshouten Talisman": 1,
            "Gypsum": 3,
            "Onigawara": 1,
            "Unkempt Hair": 10,
            "Straw Rope": 1,
            "Giant Cucumber": 10,
            "Punk Kappa Fin": 1,
            "Amagaeru Mucus": 10,
            "Amagaeru Tongue": 1
        }
    },

    "Lord Henjyo Magatama":
    {
        "Type": "Wand",
        "Level_Required": 43,
        "Chakra": 17,
        "Defence": 13,
        "Elements": null,
        "Effects":
        {
            "Skill Force": 34
        },
        "Recipe":
        {
            "Byakue Talisman": 1,
            "Metal Gear": 3,
            "Burning Water": 1,
            "Pumice Stone": 10,
            "Maple Leaf": 1,
            "Amagaeru Mucus": 10,
            "Amagaeru Tongue": 1,
            "Red Dyes": 8,
            "Red Claw": 8,
            "Bamboo Rotocoptor": 1,
            "Charcoal": 10,
            "Diamond Dust": 1
        }
    },

    "Lord Taizan Magatama":
    {
        "Type": "Wand",
        "Level_Required": 50,
        "Chakra": 20,
        "Defence": 15,
        "Elements": null,
        "Effects":
        {
            "Skill Force": 40
        },
        "Recipe":
        {
            "Daikokuten Talisman": 1,
            "Black Smoke": 3,
            "Hell's Bible": 1,
            "Crab Pearl": 10,
            "Chestnut Pearl": 1,
            "Bamboo Strip": 10,
            "Pufferfish Lantern": 2,
            "Toad Oil": 10,
            "Toad Stomach": 1,
            "Jiggling Meat": 8,
            "Melting Meat": 1
        }
    },

    "Lord Byoudou Magatama":
    {
        "Type": "Wand",
        "Level_Required": 57,
        "Chakra": 23,
        "Defence": 17,
        "Elements": null,
        "Effects":
        {
            "Skill Force": 46
        },
        "Recipe":
        {
            "Peacock Talisman": 1,
            "Shunoban Horn": 3,
            "Dried Tongue": 1,
            "Fragile Rib": 10,
            "Jaw Bone": 4,
            "Shell Fragment": 10,
            "Shirikodama": 1,
            "Centipede Eggs": 5,
            "Centipede's Poison": 1,
            "Wheel": 10,
            "Eternal Torch": 1
        }
    },

    "Lord Toshi Magatama":
    {
        "Type": "Wand",
        "Level_Required": 64,
        "Chakra": 26,
        "Defence": 19,
        "Elements": null,
        "Effects":
        {
            "Skill Force": 51
        },
        "Recipe":
        {
            "Enmaou Talisman": 1,
            "Rusted Razor": 3,
            "Nyuudou Rosary": 1,
            "Pumice Stone": 10,
            "Maple Leaf": 1,
            "Tricolor Dango": 10,
            "Broken Fishing Rod": 3,
            "Wriggling Moss": 1,
            "Toad Oil": 10,
            "Toad Stomach": 1,
            "Dark Oil": 10,
            "Waxen Fragment": 3,
            "Magical Staff": 1
        }
    },

    "Lord Godoutenrin Magatama":
    {
        "Type": "Wand",
        "Level_Required": 71,
        "Chakra": 28,
        "Defence": 21,
        "Elements": null,
        "Effects":
        {
            "Skill Force": 57
        }
    },

    "Lord Renge Magatama":
    {
        "Type": "Wand",
        "Level_Required": 79,
        "Chakra": 32,
        "Defence": 24,
        "Elements": null,
        "Effects":
        {
            "Skill Force": 63
        }
    },

    "Lord Gion Magatama":
    {
        "Type": "Wand",
        "Level_Required": 86,
        "Chakra": 34,
        "Defence": 26,
        "Elements": null,
        "Effects":
        {
            "Skill Force": 69
        }
    },

    "Lord Houkai Magatama":
    {
        "Type": "Wand",
        "Level_Required": 93,
        "Chakra": 37,
        "Defence": 28,
        "Elements": null,
        "Effects":
        {
            "Skill Force": 74
        }
    },

    "Magic Magatama":
    {
        "Type": "Wand",
        "Level_Required": 100,
        "Chakra": 40,
        "Defence": 30,
        "Elements": null,
        "Effects":
        {
            "Skill Force": 80
        }
    },

    "Talon Breaker Magatama":
    {
        "Type": "Wand",
        "Level_Required": 105,
        "Chakra": 42,
        "Defence": 31,
        "Elements": {"Dark": true, "Holy": false},
        "Effects":
        {
            "Skill Force": 100
        }
    },

    "Talon Breaker Magatama - Fused":
    {
        "Type": "Wand",
        "Level_Required": 117,
        "Chakra": 47,
        "Defence": 35,
        "Elements": {"Dark": true, "Fire": true, "Holy": false, "Rain": false},
        "Effects":
        {
            "Skill Force": 120
        }
    },

    "Talon Breaker Magatama - Tempest":
    {
        "Type": "Wand",
        "Level_Required": 128,
        "Chakra": 51,
        "Defence": 38,
        "Elements": {"Dark": true, "Fire": true, "Holy": false, "Rain": false},
        "Effects":
        {
            "Skill Force": 170
        }
    },

    "Kousei Magatama":
    {
        "Type": "Staff",
        "Level_Required": 8,
        "Chakra": 3,
        "Defence": 2,
        "Elements": null,
        "Effects":
        {
            "Skill Force": 6
        },
        "Recipe":
        {
            "Oak Staff": 1,
            "Daruma's Pipe": 3,
            "Embroidered Cushion": 1,
            "Bamboo Strip": 10,
            "Pufferfish Lantern": 2,
            "Life Daruma Fragment": 10,
            "Gift Bag": 1
        }
    },

    "Sekisei Magatama":
    {
        "Type": "Staff",
        "Level_Required": 17,
        "Chakra": 7,
        "Defence": 5,
        "Elements": null,
        "Effects":
        {
            "Skill Force": 14
        },
        "Recipe":
        {
            "Plum Staff": 1,
            "Stained Bandage": 3,
            "Kibidango": 1,
            "Dark Oil": 10,
            "Waxen Fragment": 3,
            "Magical Staff": 1,
            "Centipede Eggs": 5,
            "Centipede's Poison": 1
        }
    },

    "Kouryuu Magatama":
    {
        "Type": "Staff",
        "Level_Required": 25,
        "Chakra": 10,
        "Defence": 7,
        "Elements": null,
        "Effects":
        {
            "Skill Force": 20
        },
        "Recipe":
        {
            "Kashi Staff": 1,
            "Hiderigami's Sigh": 3,
            "Scorching Furnace": 1,
            "Crest Fragment": 10,
            "Rotted Helm": 1,
            "Baby Centipede Feelers": 10,
            "Putrid Gastric Juice": 1,
            "Jiggling Meat": 8,
            "Melting Meat": 1
        }
    },

    "Taiitsu Magatama":
    {
        "Type": "Staff",
        "Level_Required": 33,
        "Chakra": 13,
        "Defence": 10,
        "Elements": null,
        "Effects":
        {
            "Skill Force": 26
        },
        "Recipe":
        {
            "Tea Oak Staff": 1,
            "Sulfur": 3,
            "Reversed Compass": 1,
            "Crab Pearl": 10,
            "Chestnut Pearl": 1,
            "Life Daruma Fragment": 10,
            "Gift Bag": 1,
            "Spirit Mirror Shard": 10,
            "Eternal Cloud": 1
        }
    },

    "Gyokutei Magatama":
    {
        "Type": "Staff",
        "Level_Required": 42,
        "Chakra": 17,
        "Defence": 13,
        "Elements": null,
        "Effects":
        {
            "Skill Force": 34
        },
        "Recipe":
        {
            "Whitecap Staff": 1,
            "Golden Helm Fragment": 3,
            "Raisins": 1,
            "Cotton Strip": 10,
            "Fine Cloth": 2,
            "New Fundoshi": 1,
            "Unkempt Hair": 10,
            "Straw Rope": 1,
            "Spirit Mirror Shard": 10,
            "Eternal Cloud": 1,
            "Baby Centipede Feelers": 10,
            "Putrid Gastric Juice": 1
        }
    },

    "Reihou Magatama":
    {
        "Type": "Staff",
        "Level_Required": 50,
        "Chakra": 20,
        "Defence": 15,
        "Elements": null,
        "Effects":
        {
            "Skill Force": 40
        },
        "Recipe":
        {
            "Pearl Staff": 1,
            "Dried Seaweed": 3,
            "Crab Meat": 2,
            "Cursed Crab Claws": 1,
            "Wild Plants": 10,
            "Rock Roots": 1,
            "Baby Centipede Feelers": 10,
            "Putrid Gastric Juice": 1,
            "Bristly Beard": 10,
            "Tanuki Tail": 1,
            "Dark Oil": 10,
            "Waxen Fragment": 3,
            "Magical Staff": 1
        }
    },

    "Doukou Magatama":
    {
        "Type": "Staff",
        "Level_Required": 58,
        "Chakra": 23,
        "Defence": 17,
        "Elements": null,
        "Effects":
        {
            "Skill Force": 46
        },
        "Recipe":
        {
            "Flourite Staff": 1,
            "Sickle Whetstone": 3,
            "Herbissacre": 1,
            "Centipede Feelers": 10,
            "Centidote": 1,
            "Old Thread": 10,
            "Bell of the Curse God": 1,
            "Iron Sand": 10,
            "Nue Heart": 1,
            "Centipede Fluids": 10,
            "Potent Venom": 1
        }
    },

    "Doutoku Magatama":
    {
        "Type": "Staff",
        "Level_Required": 67,
        "Chakra": 27,
        "Defence": 20,
        "Elements": null,
        "Effects":
        {
            "Skill Force": 54
        },
        "Recipe":
        {
            "Ivory Staff": 1,
            "New Pacifier": 3,
            "Skull Remote": 2,
            "Green Doppelganger Mushroom": 1,
            "Red Dyes": 8,
            "Red Claw": 8,
            "Bamboo Rotocoptor": 1,
            "Old Thread": 10,
            "Bell of the Curse God": 1,
            "Gypsum": 10,
            "Onigawara": 1,
            "Cotton Strip": 10,
            "Fine Cloth": 2,
            "New Fundoshi": 1
        }
    },

    "Kuryuu Magatama":
    {
        "Type": "Staff",
        "Level_Required": 75,
        "Chakra": 30,
        "Defence": 22,
        "Elements": null,
        "Effects":
        {
            "Skill Force": 60
        }
    },

    "Kouhou Magatama":
    {
        "Type": "Staff",
        "Level_Required": 83,
        "Chakra": 33,
        "Defence": 25,
        "Elements": null,
        "Effects":
        {
            "Skill Force": 66
        }
    },

    "Fugen Magatama":
    {
        "Type": "Staff",
        "Level_Required": 92,
        "Chakra": 37,
        "Defence": 28,
        "Elements": null,
        "Effects":
        {
            "Skill Force": 74
        }
    },

    "Fake Staff Magatama":
    {
        "Type": "Staff",
        "Level_Required": 100,
        "Chakra": 40,
        "Defence": 30,
        "Elements": null,
        "Effects":
        {
            "Skill Force": 80
        }
    },

    "Crucifix Magatama":
    {
        "Type": "Staff",
        "Level_Required": 105,
        "Chakra": 42,
        "Defence": 31,
        "Elements": {"Holy": true, "Dark": false},
        "Effects":
        {
            "Skill Force": 100
        }
    },

    "Crucifix Magatama - Fused":
    {
        "Type": "Staff",
        "Level_Required": 117,
        "Chakra": 47,
        "Defence": 35,
        "Elements": {"Holy": true, "Rain": true, "Dark": false, "Lightning": false},
        "Effects":
        {
            "Skill Force": 120
        }
    },

    "Crucifix Magatama - Tempest":
    {
        "Type": "Staff",
        "Level_Required": 128,
        "Chakra": 51,
        "Defence": 38,
        "Elements": {"Holy": true, "Rain": true, "Dark": false, "Lightning": false},
        "Effects":
        {
            "Skill Force": 170
        }
    },

    "Kanetsugu Magatama":
    {
        "Type": "Critical",
        "Level_Required": 8,
        "Chakra": 3,
        "Defence": 0,
        "Elements": null,
        "Effects":
        {
            "Critical": 3
        },
        "Recipe":
        {
            "Fortitude Stone": 1,
            "Miracle Stone": 1,
            "Inferno Stone": 1,
            "Ice Stone": 1,
            "Thunder Stone": 1,
            "Light Stone": 1,
            "Dark Stone": 1,
            "Cutting Stone": 1,
            "Piercing Stone": 1,
            "Crushing Horn Stone": 1,
            "Daruma's Pipe": 3,
            "Embroidered Cushion": 1,
            "Fragile Rib": 5,
            "Gloom Daruma Fragment": 5,
            "Refreshing Leaf": 5,
            "Pain Daruma Fragment": 5,
            "Bug Repellant Coil": 5,
            "Pumice Stone": 5,
            "Luck Daruma Fragment": 5,
            "Mountain Water": 5,
            "Orange Peel Juice": 5,
            "Shell Fragment": 5,
            "Cotton Strip": 5,
            "Water Plant": 5,
            "Amagaeru Mucus": 5,
            "Crest Fragment": 5,
            "Bamboo Strip": 5,
            "Life Daruma Fragment": 5,
            "Bristly Beard": 5
        }
    },

    "Kojyuurou Magatama":
    {
        "Type": "Critical",
        "Level_Required": 17,
        "Chakra": 7,
        "Defence": 0,
        "Elements": null,
        "Effects":
        {
            "Critical": 6
        },
        "Recipe":
        {
            "Kanetsugu Magatama": 1,
            "Stained Bandage": 3,
            "Kibidango": 1,
            "Water Plant": 5,
            "Shell Fragment": 5,
            "Amagaeru Mucus": 5,
            "Toad Oil": 5,
            "Jiggling Meat": 5,
            "Tricolor Dango": 5,
            "Giant Cucumber": 5,
            "Bristly Beard": 5,
            "Crest Fragment": 5,
            "Fragile Rib": 5,
            "Bamboo Strip": 5,
            "Mountain Water": 5,
            "Baby Centipede Feelers": 5,
            "Orange Peel Juice": 5,
            "Dark Oil": 5,
            "Centipede Eggs": 5
        }
    },

    "Michizane Magatama":
    {
        "Type": "Critical",
        "Level_Required": 25,
        "Chakra": 10,
        "Defence": 0,
        "Elements": null,
        "Effects":
        {
            "Critical": 8
        },
        "Recipe":
        {
            "Kojyuurou Magatama": 1,
            "Black Moth Scales": 3,
            "Gray Apple": 1,
            "Fragile Rib": 5,
            "Mountain Water": 5,
            "Crest Fragment": 5,
            "Baby Centipede Feelers": 5,
            "Jiggling Meat": 5,
            "Water Plant": 5,
            "Shell Fragment": 5,
            "Giant Cucumber": 5,
            "Amagaeru Mucus": 5,
            "Toad Oil": 5,
            "Gloom Daruma Fragment": 5,
            "Tart Peach": 5,
            "Dark Oil": 5,
            "Cat Whiskers": 5,
            "Life Daruma Fragment": 5,
            "Bamboo Strip": 5,
            "Luck Daruma Fragment": 5,
            "Loss Daruma Fragment": 5,
            "Bristly Beard": 5,
            "Gypsum": 5,
            "Crow Feather": 5,
            "Spirit Mirror Shard": 5
        }
    },

    "Yukimura Magatama":
    {
        "Type": "Critical",
        "Level_Required": 33,
        "Chakra": 13,
        "Defence": 0,
        "Elements": null,
        "Effects":
        {
            "Critical": 11
        },
        "Recipe":
        {
            "Michizane Magatama": 1,
            "Sulfur": 3,
            "Reversed Compass": 1,
            "Dark Oil": 5,
            "Broken Lantern": 5,
            "Red Scale": 5,
            "Bamboo Strip": 5,
            "Baby Centipede Feelers": 5,
            "Baby Fly Wings": 5,
            "Fragile Rib": 5,
            "Unkempt Hair": 5,
            "Giant Cucumber": 5,
            "Amagaeru Mucus": 5,
            "Crab Pearl": 5,
            "Life Daruma Fragment": 5,
            "Spirit Mirror Shard": 5,
            "Yagyou-san's Tears":  5,
            "Bristly Beard": 5,
            "Gypsum": 5,
            "Crest Fragment": 5,
            "Luck Daruma Fragment": 5,
            "Loss Daruma Fragment": 5,
            "Mountain Water": 5,
            "Jiggling Meat": 5,
            "Black Body Hair": 5,
            "Centipede Fluids": 5
        }
    },

    "Shingen Magatama":
    {
        "Type": "Critical",
        "Level_Required": 42,
        "Chakra": 17,
        "Defence": 0,
        "Elements": null,
        "Effects":
        {
            "Critical": 14
        },
        "Recipe":
        {
            "Yukimura Magatama": 1,
            "Golden Helm Fragment": 3,
            "Raisins": 1,
            "Cotton Strip": 5,
            "Unkempt Hair": 5,
            "Spirit Mirror Shard": 5,
            "Baby Centipede Feelers": 5,
            "Toad Oil": 5,
            "Giant Cucumber": 5,
            "Fragile Rib": 5,
            "Gloom Daruma Fragment": 5,
            "Luck Daruma Fragment": 5,
            "Loss Daruma Fragment": 5,
            "Mountain Water": 5,
            "Crow Feather": 5,
            "Crest Fragment": 5,
            "Jiggling Meat": 5,
            "Black Body Hair": 5,
            "Cat Whiskers": 5,
            "Red Scale": 5,
            "Old Thread": 5,
            "Paper Helmet": 5,
            "Paper Helmet": 5,
            "Paper Crane": 5,
            "Iron Sand": 5,
            "Ashes": 5,
            "Bamboo Strip": 5,
            "Pumice Stone": 5,
            "Amagaeru Mucus": 5,
            "Red Dyes": 5,
            "Red Claw": 5,
            "Charcoal": 5
        }
    },

    "Kenshin Magatama":
    {
        "Type": "Critical",
        "Level_Required": 50,
        "Chakra": 20,
        "Defence": 0,
        "Elements": null,
        "Effects":
        {
            "Critical": 17
        },
        "Recipe":
        {
            "Shingen Magatama": 1,
            "Spiked Collar": 3,
            "Honey": 2,
            "Cerberus Vinegar": 1,
            "Giant Cucumber": 5,
            "Amagaeru Mucus": 5,
            "Crab Pearl": 5,
            "Bamboo Strip": 5,
            "Toad Oil": 5,
            "Jiggling Meat": 5,
            "Fragile Rib": 5,
            "Shell Fragment": 5,
            "Centipede Eggs": 5,
            "Wheel": 5,
            "Wild Plants": 5,
            "Baby Centipede Feelers": 5,
            "Bristly Beard": 5,
            "Dark Oil": 5,
            "Centipede Feelers": 5,
            "Old Thread": 5,
            "Iron Sand": 5,
            "Centipede Fluids": 5,
            "Charcoal": 5,
            "Bug Repellant Coil": 5,
            "Red Scale": 5,
            "Nozuchi Stomach Acid": 5,
            "Spirit Mirror Shard": 5,
            "Unkempt Hair": 5,
            "Black Body Hair": 5,
            "Withering Spirit": 5
        }
    },

    "Nobunaga Magatama":
    {
        "Type": "Critical",
        "Level_Required": 58,
        "Chakra": 23,
        "Defence": 0,
        "Elements": null,
        "Effects":
        {
            "Critical": 19
        },
        "Recipe":
        {
            "Kenshin Magatama": 1,
            "Black Smoke": 3,
            "Hell's Bible": 1,
            "Giant Cucumber": 5,
            "Amagaeru Mucus": 5,
            "Crab Pearl": 5,
            "Bamboo Strip": 5,
            "Toad Oil": 5,
            "Jiggling Meat": 5,
            "Fragile Rib": 5,
            "Shell Fragment": 5,
            "Centipede Eggs": 5,
            "Wheel": 5,
            "Wild Plants": 5,
            "Baby Centipede Feelers": 5,
            "Bristly Beard": 5,
            "Dark Oil": 5,
            "Centipede Feelers": 5,
            "Old Thread": 5,
            "Iron Sand": 5,
            "Centipede Fluids": 5,
            "Charcoal": 5,
            "Bug Repellant Coil": 5,
            "Red Scale": 5,
            "Nozuchi Stomach Acid": 5,
            "Spirit Mirror Shard": 5,
            "Unkempt Hair": 5,
            "Black Body Hair": 5,
            "Withering Spirit": 5
        }
    },

    "Masakado Magatama":
    {
        "Type": "Critical",
        "Level_Required": 67,
        "Chakra": 27,
        "Defence": 0,
        "Elements": null,
        "Effects":
        {
            "Critical": 22
        },
        "Recipe":
        {
            "Nobunaga Magatama": 1,
            "Tep Extract": 3,
            "Tep Flute": 3,
            "Chaos Wasabi": 2,
            "Lively Bulb": 1,
            "Fragile Rib": 5,
            "Bamboo Strip": 5,
            "Centipede Eggs": 5,
            "Baby Centipede Feelers": 5,
            "Black Body Hair": 5,
            "Withering Spirit": 5,
            "Red Scale": 5,
            "Wild Plants": 5,
            "Centipede Fluids": 5,
            "Refreshing Leaf": 5,
            "Pumice Stone": 5,
            "Tricolor Dango": 5,
            "Toad Oil": 5,
            "Dark Oil": 5,
            "Red Dyes": 5,
            "Red Claw": 5,
            "Old Thread": 5,
            "Gypsum": 5,
            "Cotton Strip": 5,
            "Unkempt Hair": 5,
            "Shell Fragment": 5,
            "Jiggling Meat": 5,
            "Baby Bottle": 5,
            "Dried Seaweed": 5,
            "Crab Pearl": 5,
            "Nozuchi Stomach Acid": 5,
            "Crest Fragment": 5,
            "Giant Cucumber": 5,
            "Broken Lantern": 5,
            "Fletching": 5,
            "Charcoal": 5
        }
    },

    "Hanzou Magatama":
    {
        "Type": "Critical",
        "Level_Required": 75,
        "Chakra": 30,
        "Defence": 0,
        "Elements": null,
        "Effects":
        {
            "Critical": 25
        }
    },

    "Masamune Magatama":
    {
        "Type": "Critical",
        "Level_Required": 83,
        "Chakra": 33,
        "Defence": 0,
        "Elements": null,
        "Effects":
        {
            "Critical": 28
        }
    },

    "Tadakatsu Magatama":
    {
        "Type": "Critical",
        "Level_Required": 92,
        "Chakra": 37,
        "Defence": 0,
        "Elements": null,
        "Effects":
        {
            "Critical": 31
        }
    },

    "Kiyomasa Magatama":
    {
        "Type": "Critical",
        "Level_Required": 100,
        "Chakra": 40,
        "Defence": 0,
        "Elements": null,
        "Effects":
        {
            "Critical": 33
        }
    },

    "Masanori Magatama":
    {
        "Type": "Critical",
        "Level_Required": 108,
        "Chakra": 43,
        "Defence": 0,
        "Elements": null,
        "Effects":
        {
            "Critical": 36
        }
    },

    "Katsuie Magatama":
    {
        "Type": "Critical",
        "Level_Required": 117,
        "Chakra": 47,
        "Defence": 0,
        "Elements": null,
        "Effects":
        {
            "Critical": 39
        }
    },

    "Nagayoshi Magatama":
    {
        "Type": "Critical",
        "Level_Required": 125,
        "Chakra": 50,
        "Defence": 0,
        "Elements": null,
        "Effects":
        {
            "Critical": 42
        }
    },

    "Naomasa Magatama":
    {
        "Type": "Critical",
        "Level_Required": 133,
        "Chakra": 53,
        "Defence": 0,
        "Elements": null,
        "Effects":
        {
            "Critical": 44
        }
    },

    "Yoshihiro Magatama":
    {
        "Type": "Critical",
        "Level_Required": 142,
        "Chakra": 57,
        "Defence": 0,
        "Elements": null,
        "Effects":
        {
            "Critical": 47
        }
    },

    "Dousetsu Magatama":
    {
        "Type": "Critical",
        "Level_Required": 150,
        "Chakra": 60,
        "Defence": 0,
        "Elements": null,
        "Effects":
        {
            "Critical": 50
        }
    },

    "Chiami Magatama x1":
    {
        "Type": "Omni",
        "Level_Required": 15,
        "Chakra": 6,
        "Defence": 0,
        "Elements": null,
        "Effects":
        {
            "Heal": 10
        },
        "Comment": "Heals 10% of HP when a critical hit is dealt"
    },

    "Chiami Magatama x2":
    {
        "Type": "Omni",
        "Level_Required": 30,
        "Chakra": 12,
        "Defence": 0,
        "Elements": null,
        "Effects":
        {
            "Heal": 20
        },
        "Comment": "Heals 20% of HP when a critical hit is dealt"
    },

    "Chiami Magatama x3":
    {
        "Type": "Omni",
        "Level_Required": 45,
        "Chakra": 18,
        "Defence": 0,
        "Elements": null,
        "Effects":
        {
            "Heal": 30
        },
        "Comment": "Heals 30% of HP when a critical hit is dealt"
    },

    "Chiami Magatama x4":
    {
        "Type": "Omni",
        "Level_Required": 60,
        "Chakra": 24,
        "Defence": 0,
        "Elements": null,
        "Effects":
        {
            "Heal": 40
        },
        "Comment": "Heals 40% of HP when a critical hit is dealt"
    },

    "Chiami Magatama x5":
    {
        "Type": "Omni",
        "Level_Required": 75,
        "Chakra": 30,
        "Defence": 0,
        "Elements": null,
        "Effects":
        {
            "Heal": 50
        },
        "Comment": "Heals 50% of HP when a critical hit is dealt"
    },

    "Chiami Magatama x6":
    {
        "Type": "Omni",
        "Level_Required": 90,
        "Chakra": 36,
        "Defence": 0,
        "Elements": null,
        "Effects":
        {
            "Heal": 60
        },
        "Comment": "Heals 60% of HP when a critical hit is dealt"
    },

    "Chiami Magatama x7":
    {
        "Type": "Omni",
        "Level_Required": 105,
        "Chakra": 42,
        "Defence": 0,
        "Elements": null,
        "Effects":
        {
            "Heal": 70
        },
        "Comment": "Heals 70% of HP when a critical hit is dealt"
    },

    "Chiami Magatama x8":
    {
        "Type": "Omni",
        "Level_Required": 120,
        "Chakra": 48,
        "Defence": 0,
        "Elements": null,
        "Effects":
        {
            "Heal": 80
        },
        "Comment": "Heals 80% of HP when a critical hit is dealt"
    },

    "Chiami Magatama x9":
    {
        "Type": "Omni",
        "Level_Required": 135,
        "Chakra": 54,
        "Defence": 0,
        "Elements": null,
        "Effects":
        {
            "Heal": 90
        },
        "Comment": "Heals 90% of HP when a critical hit is dealt"
    },

    "Chiami Magatama x10":
    {
        "Type": "Omni",
        "Level_Required": 150,
        "Chakra": 60,
        "Defence": 0,
        "Elements": null,
        "Effects":
        {
            "Heal": 100
        },
        "Comment": "Heals 100% of HP when a critical hit is dealt"
    },

    "Haidara Magatama":
    {
        "Type": "Omni",
        "Level_Required": 50,
        "Chakra": 20,
        "Defence": 0,
        "Elements": null,
        "Effects":
        {
            "Critical Immunity": true
        },
        "Recipe":
        {
            "Fortitude Stone": 1,
            "Miracle Stone": 1,
            "Inferno Stone": 1,
            "Ice Stone": 1,
            "Thunder Stone": 1,
            "Light Stone": 1,
            "Dark Stone": 1,
            "Cutting Stone": 1,
            "Piercing Stone": 1,
            "Crushing Horn Stone": 1,
            "Black Smoke": 3,
            "Hell's Bible": 1,
            "Spiked Collar": 3,
            "Honey": 2,
            "Cerberus Vinegar": 1,
            "Sickle Whetstone": 3,
            "Herbissacre": 1
        },
        "Comment": "Immune to critical hits"
    }
}
